pgdock/__init__.py
pgdock/cli.py
pgdock/utils.py
pgdock-1.0.0.dist-info/licenses/LICENSE
pgdock-1.0.0.dist-info/METADATA
pgdock-1.0.0.dist-info/WHEEL
pgdock-1.0.0.dist-info/entry_points.txt
pgdock-1.0.0.dist-info/top_level.txt
pgdock-1.0.0.dist-info/RECORD
