Metadata-Version: 2.4
Name: pgdock
Version: 1.0.0
Summary: PostgreSQL Docker Instance Manager CLI. Create, manage, and backup PostgreSQL instances with automatic credential generation, health monitoring, and cross-platform support.
Author: pgdock
Author-email: Matija <your-email@example.com>
Project-URL: Homepage, https://github.com/matija2209/pgdock
Project-URL: Repository, https://github.com/matija2209/pgdock
Project-URL: Issues, https://github.com/matija2209/pgdock/issues
Project-URL: Documentation, https://github.com/matija2209/pgdock#readme
Keywords: postgresql,docker,cli,database,postgres,docker-compose,backup,instance-manager
Classifier: Development Status :: 4 - Beta
Classifier: Intended Audience :: Developers
Classifier: License :: OSI Approved :: MIT License
Classifier: Operating System :: OS Independent
Classifier: Programming Language :: Python :: 3
Classifier: Programming Language :: Python :: 3.10
Classifier: Programming Language :: Python :: 3.11
Classifier: Programming Language :: Python :: 3.12
Classifier: Topic :: Database
Classifier: Topic :: System :: Systems Administration
Classifier: Topic :: Software Development :: Libraries :: Python Modules
Classifier: Environment :: Console
Requires-Python: >=3.10
License-File: LICENSE
Requires-Dist: typer>=0.12.0
Requires-Dist: pyyaml>=6.0
Requires-Dist: jinja2>=3.1.0
Requires-Dist: rich>=13.0.0
Requires-Dist: click>=8.0.0
Dynamic: author
Dynamic: license-file
Dynamic: requires-python
